Metadata-Version: 2.1
Name: evatool
Version: 0.1.21
Summary: Extracellular Vesicles small RNAs Abundance and quantification tool
Home-page: https://github.com/xieguiyan/EVAtool
Author: Dr. Xie and Dr. Liu
Author-email: xieguiyan@hust.eud.cn
License: MIT
Keywords: evatool,small ncRNA,abundance,quantification
Platform: any
Requires-Python: >=3.5
License-File: LICENSE
Requires-Dist: numpy (>=1.15)
Requires-Dist: pandas
Requires-Dist: seaborn (>=0.9.0)
Requires-Dist: jinja2
Provides-Extra: dev
Requires-Dist: pytest ; extra == 'dev'
Requires-Dist: pytest-cov ; extra == 'dev'
Requires-Dist: pytest-mock ; extra == 'dev'
Requires-Dist: pytest-xdist ; extra == 'dev'
Requires-Dist: tox ; extra == 'dev'
Provides-Extra: interactive
Requires-Dist: matplotlib ; extra == 'interactive'
